apis_core/.DS_Store
apis_core/.vscode/settings.json
apis_core/__init__.py
apis_core/api_renderers.py
apis_core/api_routers.py
apis_core/apis_entities/__init__.py
apis_core/apis_entities/admin.py
apis_core/apis_entities/api_mappings/__init__.py
apis_core/apis_entities/api_mappings/cidoc_mapping.py
apis_core/apis_entities/api_renderers.py
apis_core/apis_entities/api_urls.py
apis_core/apis_entities/api_views.py
apis_core/apis_entities/apps.py
apis_core/apis_entities/autocomplete3.py
apis_core/apis_entities/autocomplete_light_registry.py
apis_core/apis_entities/custom_authentication.py
apis_core/apis_entities/custom_autocompletes.py
apis_core/apis_entities/detail_views.py
apis_core/apis_entities/fields.py
apis_core/apis_entities/filters.py
apis_core/apis_entities/fixtures/db_v2.json
apis_core/apis_entities/fixtures/db_v5.json
apis_core/apis_entities/fixtures/fixtures_3_5_17.json
apis_core/apis_entities/forms.py
apis_core/apis_entities/management/commands/normalize_uris.py
apis_core/apis_entities/management/commands/resolve_abbreviations.py
apis_core/apis_entities/management/commands/serialize_to_cidoc.py
apis_core/apis_entities/management/commands/serialize_to_json.py
apis_core/apis_entities/merge_views.py
apis_core/apis_entities/migrations/0001_initial.py
apis_core/apis_entities/migrations/0002_auto_20200121_1227.py
apis_core/apis_entities/migrations/0003_auto_20200216_1152.py
apis_core/apis_entities/migrations/0004_auto_20200722_1231.py
apis_core/apis_entities/migrations/__init__.py
apis_core/apis_entities/models.py
apis_core/apis_entities/serializers.py
apis_core/apis_entities/serializers_generic.py
apis_core/apis_entities/static/apis_entities/libraries/bower.json
apis_core/apis_entities/tables.py
apis_core/apis_entities/templates/apis_entities/apis_create_entities.html
apis_core/apis_entities/templates/apis_entities/apis_templatetag.html
apis_core/apis_entities/templates/apis_entities/compare_base.html
apis_core-0.18.14.dist-info/LICENSE.txt
apis_core-0.18.14.dist-info/METADATA
apis_core-0.18.14.dist-info/WHEEL
apis_core-0.18.14.dist-info/RECORD
