Metadata-Version: 2.1
Name: apis-core
Version: 0.18.14
Summary: Base package for the APIS framework
License: MIT
Author: Matthias Schlögl
Author-email: matthias.schloegl@oeaw.ac.at
Requires-Python: >=3.7,<3.11
Classifier: License :: OSI Approved :: MIT License
Classifier: Programming Language :: Python :: 3
Classifier: Programming Language :: Python :: 3.7
Classifier: Programming Language :: Python :: 3.8
Classifier: Programming Language :: Python :: 3.9
Classifier: Programming Language :: Python :: 3.10
Requires-Dist: Django (>=3.1.8,<3.2.0)
Requires-Dist: PyYAML (>=5.3.1,<6.0.0)
Requires-Dist: SPARQLWrapper (>=1.8.5,<2.0.0)
Requires-Dist: convertdate (>=2.3.0,<3.0.0)
Requires-Dist: dj-database-url (>=0.5.0,<0.6.0)
Requires-Dist: django-admin-csvexport (>=1.9,<2.0)
Requires-Dist: django-autocomplete-light (>=3.8.2,<3.9.0)
Requires-Dist: django-cors-headers (>=3.5.0,<4.0.0)
Requires-Dist: django-crispy-forms (>=1.10.0,<2.0.0)
Requires-Dist: django-crum (>=0.7.9,<0.8.0)
Requires-Dist: django-filter (>=2.4.0,<3.0.0)
Requires-Dist: django-gm2m (>=1.1.1,<2.0.0)
Requires-Dist: django-guardian (>=2.3.0,<3.0.0)
Requires-Dist: django-leaflet (>=0.27.1,<0.28.0)
Requires-Dist: django-model-utils (>=4.1.1,<5.0.0)
Requires-Dist: django-reversion (>=3.0.8,<4.0.0)
Requires-Dist: django-summernote (>=0.8.11,<0.9.0)
Requires-Dist: django-tables2 (>=2.3.3,<3.0.0)
Requires-Dist: djangorestframework (>=3.14.0,<4.0.0)
Requires-Dist: djangorestframework-csv (>=2.1.0,<3.0.0)
Requires-Dist: djangorestframework-jsonschema (>=0.1.1,<0.2.0)
Requires-Dist: djangorestframework-xml (>=2.0.0,<3.0.0)
Requires-Dist: drf-spectacular (>=0.26.1,<0.27.0)
Requires-Dist: jmespath (>=0.10.0,<0.11.0)
Requires-Dist: jsonschema (>=3.2.0,<4.0.0)
Requires-Dist: lxml (>=4.6.2,<5.0.0)
Requires-Dist: mysqlclient (>=2.0.3,<3.0.0)
Requires-Dist: pandas (>=1.1.5,<2)
Requires-Dist: rdflib (>=6.1.1,<6.2.0)
Requires-Dist: regex (>=2020.11.13,<2021.0.0)
Requires-Dist: requests (>=2.25.0,<3.0.0)
Requires-Dist: tablib (>=3.0.0,<4.0.0)
Requires-Dist: tqdm (>=4.62.3,<5.0.0)
Requires-Dist: unicodecsv (>=0.14.1,<0.15.0)
